beamframe/SingularityFunction.py
beamframe/__init__.py
beamframe/beam.py
beamframe-0.1.1.dist-info/LICENSE.txt
beamframe-0.1.1.dist-info/METADATA
beamframe-0.1.1.dist-info/WHEEL
beamframe-0.1.1.dist-info/top_level.txt
beamframe-0.1.1.dist-info/RECORD
