Metadata-Version: 2.1
Name: beamframe
Version: 0.1.1
Summary: A python module to solve and analyse determinate 2d Beams.
Home-page: https://ashimp.com.np/beamframe/
Author: Ashim Paudel
Author-email: paudelashim111@gmail.com
Project-URL: Source, https://github.com/Ashim-Paudel/Python-Beam-Analysis
Project-URL: Bug Reports, https://github.com/Ashim-Paudel/Python-Beam-Analysis/issues
Project-URL: Funding, https://ashimp.com.np/beamframe/
Project-URL: Say Thanks!, http://ashimp.com.np/#contact
Keywords: beams,frames,structure,civil engineering,structural engineering,applied mechanics
Classifier: Development Status :: 3 - Alpha
Classifier: Topic :: Scientific/Engineering :: Visualization
Classifier: Topic :: Scientific/Engineering :: Physics
Classifier: License :: OSI Approved :: MIT License
Requires-Python: >=3.4, <4
License-File: LICENSE.txt
Requires-Dist: numpy (>=1.19)
Requires-Dist: sympy (>=1)
Requires-Dist: matplotlib (>=3)
